MANIFEST.in
README.md
setup.py
ddb3cython/__init__.py
ddb3cython/cli.c
ddb3cython/engine.c
ddb3cython/interactive.c
ddb3cython/version.c
ddb3cython/version.py
ddb3cython.egg-info/PKG-INFO
ddb3cython.egg-info/SOURCES.txt
ddb3cython.egg-info/dependency_links.txt
ddb3cython.egg-info/entry_points.txt
ddb3cython.egg-info/top_level.txt
ddb3cython/configuration/__init__.py
ddb3cython/configuration/column.c
ddb3cython/configuration/database.c
ddb3cython/configuration/table.c
ddb3cython/file_io/__init__.py
ddb3cython/file_io/locking.c
ddb3cython/functions/__init__.py
ddb3cython/functions/functions.c
ddb3cython/lexer/__init__.py
ddb3cython/lexer/language.c
ddb3cython/lexer/lexer.c
ddb3cython/lexer/tokenize.c
ddb3cython/meta/__init__.py
ddb3cython/meta/meta.c
ddb3cython/methods/__init__.py
ddb3cython/methods/database_show_errors.c
ddb3cython/methods/database_use.c
ddb3cython/methods/record.c
ddb3cython/methods/record_core.c
ddb3cython/methods/record_delete.c
ddb3cython/methods/record_insert.c
ddb3cython/methods/record_select.c
ddb3cython/methods/record_update.c
ddb3cython/methods/record_upsert.c
ddb3cython/methods/system_begin.c
ddb3cython/methods/system_commit.c
ddb3cython/methods/system_rollback.c
ddb3cython/methods/system_set.c
ddb3cython/methods/system_show_columns.c
ddb3cython/methods/system_show_output_modules.c
ddb3cython/methods/system_show_tables.c
ddb3cython/methods/system_show_variables.c
ddb3cython/methods/table_create.c
ddb3cython/methods/table_describe.c
ddb3cython/methods/table_drop.c
ddb3cython/methods/table_update.c
ddb3cython/output/__init__.py
ddb3cython/output/factory.c
ddb3cython/output/factory_json.c
ddb3cython/output/factory_term.c
ddb3cython/output/factory_xml.c
ddb3cython/output/factory_yaml.c